stagedoor/__init__.py
stagedoor/admin.py
stagedoor/apps.py
stagedoor/backends.py
stagedoor/helpers.py
stagedoor/models.py
stagedoor/py.typed
stagedoor/settings.py
stagedoor/urls.py
stagedoor/views.py
stagedoor/migrations/0001_initial.py
stagedoor/migrations/0002_authtoken_approved.py
stagedoor/migrations/__init__.py
stagedoor/templates/stagedoor_approval_email.html
stagedoor/templates/stagedoor_approval_email.txt
stagedoor/templates/stagedoor_approval_needed.html
stagedoor/templates/stagedoor_email.html
stagedoor/templates/stagedoor_email.txt
stagedoor/templates/stagedoor_token_input.html
django_stagedoor-0.1.3.dist-info/METADATA
django_stagedoor-0.1.3.dist-info/WHEEL
django_stagedoor-0.1.3.dist-info/licenses/LICENSE
django_stagedoor-0.1.3.dist-info/RECORD
