Metadata-Version: 2.4
Name: django-stagedoor
Version: 0.1.3
Summary: Add your description here
Author-email: Philip James <phildini@phildini.net>
License-File: LICENSE
Requires-Python: >=3.10
Requires-Dist: django-phonenumber-field[phonenumbers]>=8.0.0
Requires-Dist: django>=4.2
Requires-Dist: twilio>=9.5.1
